nr_metadata/__init__.py
nr_metadata/version.py
nr_metadata/common/__init__.py
nr_metadata/common/config.py
nr_metadata/common/ext.py
nr_metadata/common/proxies.py
nr_metadata/common/version.py
nr_metadata/common/models/__init__.py
nr_metadata/common/models/records.json
nr_metadata/common/records/__init__.py
nr_metadata/common/records/api.py
nr_metadata/common/records/models.py
nr_metadata/common/records/dumpers/__init__.py
nr_metadata/common/records/dumpers/dumper.py
nr_metadata/common/records/dumpers/edtf.py
nr_metadata/common/records/dumpers/multilingual.py
nr_metadata/common/records/jsonschemas/__init__.py
nr_metadata/common/records/jsonschemas/common-1.0.0.json
nr_metadata/common/records/mappings/__init__.py
nr_metadata/common/records/mappings/os-v2/__init__.py
nr_metadata/common/records/mappings/os-v2/common/__init__.py
nr_metadata/common/records/mappings/os-v2/common/common-1.0.0.json
nr_metadata/common/resources/__init__.py
nr_metadata/common/resources/records/__init__.py
nr_metadata/common/resources/records/config.py
nr_metadata/common/resources/records/resource.py
nr_metadata/common/resources/records/ui.py
nr_metadata/common/services/__init__.py
nr_metadata/common/services/records/__init__.py
nr_metadata/common/services/records/config.py
nr_metadata/common/services/records/facets.py
nr_metadata/common/services/records/permissions.py
nr_metadata/common/services/records/results.py
nr_metadata/common/services/records/schema.py
nr_metadata/common/services/records/schema_common.py
nr_metadata/common/services/records/schema_datatypes.py
nr_metadata/common/services/records/search.py
nr_metadata/common/services/records/service.py
nr_metadata/common/services/records/ui_schema_common.py
nr_metadata/common/services/records/ui_schema_datatypes.py
nr_metadata/common/views/__init__.py
nr_metadata/common/views/records/__init__.py
nr_metadata/common/views/records/api.py
nr_metadata/common/views/records/app.py
nr_metadata/data/__init__.py
nr_metadata/data/config.py
nr_metadata-2.0.80.dist-info/METADATA
nr_metadata-2.0.80.dist-info/WHEEL
nr_metadata-2.0.80.dist-info/entry_points.txt
nr_metadata-2.0.80.dist-info/top_level.txt
nr_metadata-2.0.80.dist-info/RECORD
