Metadata-Version: 2.4
Name: nr-metadata
Version: 2.0.80
Summary: "Generated metadata files for the Czech National Repository"
Home-page: https://github.com/Narodni-repozitar/ne-metadata
Author: Miroslav Simek
Author-email: simek.miroslav@techlib.cz
License: MIT
Keywords: invenio Czech NR
Platform: any
Classifier: Development Status :: 3 - Alpha
Requires-Python: >=3.9
Requires-Dist: oarepo-runtime>=1.0.0
Requires-Dist: deepmerge>=1.1.0
Requires-Dist: oarepo-vocabularies>=2.0.0
Requires-Dist: oarepo-global-search>=1.0.23
Requires-Dist: oarepo-workflows>=1.0.0
Provides-Extra: tests
Requires-Dist: pytest; extra == "tests"
Requires-Dist: black; extra == "tests"
Requires-Dist: isort; extra == "tests"
Requires-Dist: autoflake; extra == "tests"
Requires-Dist: pytest-invenio>=1.4.11; extra == "tests"
